tests/__init__.py
tests/test_properties.py
tns_api/__init__.py
tns_api/_version.py
tns_api/api.py
tns_api/credentials.py
tns_api/utils.py
tns_api-1.1.0.dist-info/licenses/LICENSE
tns_api-1.1.0.dist-info/METADATA
tns_api-1.1.0.dist-info/WHEEL
tns_api-1.1.0.dist-info/top_level.txt
tns_api-1.1.0.dist-info/RECORD
